detector_aedes/__init__.py
detector_aedes/analyzers.py
detector_aedes/config.yml
detector_aedes/config_sample.yml
detector_aedes/connectors.py
detector_aedes/detector_aedes.py
detector_aedes/image_connectors.py
detector_aedes/old_detector_aedes.py
detector_aedes/models/aedes-model.pkl
detector_aedes-0.1.0.dist-info/DESCRIPTION.rst
detector_aedes-0.1.0.dist-info/METADATA
detector_aedes-0.1.0.dist-info/RECORD
detector_aedes-0.1.0.dist-info/WHEEL
detector_aedes-0.1.0.dist-info/metadata.json
detector_aedes-0.1.0.dist-info/top_level.txt
