Metadata-Version: 2.0
Name: detector-aedes
Version: 0.1.0
Summary: Algoritmos de Visión Computacional para analizar imágenes de Ovisensores. Edit
Home-page: https://github.com/datosgobar/detector-aedes
Author: Datos Argentina
Author-email: datos@modernizacion.gob.ar
License: MIT license
Keywords: detector_aedes
Platform: UNKNOWN
Classifier: Development Status :: 2 - Pre-Alpha
Classifier: Intended Audience :: Developers
Classifier: License :: OSI Approved :: MIT License
Classifier: Natural Language :: Spanish
Classifier: Programming Language :: Python :: 2.7
Requires-Dist: matplotlib
Requires-Dist: numpy
Requires-Dist: scikit-image
Requires-Dist: scikit-learn
